{
  "name": "AIS (M3U8)",
  "author": "update 15/4/2569",
  "image": "https://aisplay.ais.co.th/portal/static/img/ais_play.e9f424a5.png",
  "url": "https://raw.githubusercontent.com/nongakka/TV/main/ais_playlist.json",
  "stations": [
    {
      "name": "NBT 2 HD",
      "image": "https://ais-s.ais-vidnt.com/ais/play/origin/LIVE//channelicon/0001.png",
      "url": "https://49-231-37-235-rewriter.ais-vidnt.com/ais/play/anevia/live/eds/B0001/HLS/B0001.m3u8?playbackUrlPrefix=https%3A%2F%2Ftr.play-rbcdn.ais.co.th%3A8438%2F&originBasicUrl=http%3A%2F%2Fpl-origin.ais-vidnt.com%2Fais%2Fplay%2Fanevia&tt=a33524af1d8b212d7ad71ba7d84fc3cd&chunkHttps=true&tmid=B0001&tpbk=NTlh2GKNEED9qrtX&rrt=1776261502&tmod=rfk&rsid=5dc075d7-37c0-41a9-9d05-ba92d3bb0e08&tuid=09194712d8&cdn=redfox-https&tdid=8d2174919041f976a214a5ad8a720a8f&origin=anevia&tfa=f0-fc&tttl=1776347901",
      "referer": "https://49-231-34-108-rewriter.ais-vidnt.com/",
      "userAgent": "Mozilla/5.0 (Windows NT 10.0; WOW64) AppleWebKit/537.36 (KHTML, like Gecko) Chrome/69.0.3497.81 Safari/537.36 Maxthon/5.3.8.2000",
      "playInNatPlayer": "true"
    },
    {
      "name": "TPBS",
      "image": "https://ais-s.ais-vidnt.com/ais/play/origin/LIVE//channelicon/0014.png",
      "url": "https://49-231-37-37-rewriter.ais-vidnt.com/ais/play/anevia/live/eds/B0014/HLS/B0014.m3u8?playbackUrlPrefix=https%3A%2F%2Ftr.play-rbcdn.ais.co.th%3A8438%2F&originBasicUrl=http%3A%2F%2Fpl-origin.ais-vidnt.com%2Fais%2Fplay%2Fanevia&tt=a33524af1d8b212d7ad71ba7d84fc3cd&chunkHttps=true&tmid=B0014&tpbk=NTlh2GKNEED9qrtX&rrt=1776261509&tmod=rfk&rsid=297f3382-79da-4b21-b300-3210ef7d078a&tuid=09194712d8&cdn=redfox-https&tdid=8d2174919041f976a214a5ad8a720a8f&origin=anevia&tfa=f0-fc&tttl=1776347901",
      "referer": "https://49-231-34-108-rewriter.ais-vidnt.com/",
      "userAgent": "Mozilla/5.0 (Windows NT 10.0; WOW64) AppleWebKit/537.36 (KHTML, like Gecko) Chrome/69.0.3497.81 Safari/537.36 Maxthon/5.3.8.2000",
      "playInNatPlayer": "true"
    },
    {
      "name": "CH5 HD",
      "image": "https://ais-s.ais-vidnt.com/ais/play/origin/LIVE//channelicon//ch5new.logo.png",
      "url": "https://49-231-37-37-rewriter.ais-vidnt.com/ais/play/anevia/live/eds/B0007/HLS/B0007.m3u8?playbackUrlPrefix=https%3A%2F%2Ftr.play-rbcdn.ais.co.th%3A8438%2F&originBasicUrl=http%3A%2F%2Fpl-origin.ais-vidnt.com%2Fais%2Fplay%2Fanevia&tt=a33524af1d8b212d7ad71ba7d84fc3cd&chunkHttps=true&tmid=B0007&tpbk=NTlh2GKNEED9qrtX&rrt=1776261515&tmod=rfk&rsid=90463aeb-0600-40e0-9815-64fe0b24ac77&tuid=09194712d8&cdn=redfox-https&tdid=8d2174919041f976a214a5ad8a720a8f&origin=anevia&tfa=f0-fc&tttl=1776347901",
      "referer": "https://49-231-34-108-rewriter.ais-vidnt.com/",
      "userAgent": "Mozilla/5.0 (Windows NT 10.0; WOW64) AppleWebKit/537.36 (KHTML, like Gecko) Chrome/69.0.3497.81 Safari/537.36 Maxthon/5.3.8.2000",
      "playInNatPlayer": "true"
    },
    {
      "name": "T-Sports 7",
      "image": "https://ais-s.ais-vidnt.com/ais/play/origin/LIVE/channelicon/T-SPorts_7_Final.png",
      "url": "https://49-231-34-109-rewriter.ais-vidnt.com/ais/play/anevia/live/eds/B0129/HLS/B0129.m3u8?playbackUrlPrefix=https%3A%2F%2Ftr.play-rbcdn.ais.co.th%3A8438%2F&originBasicUrl=http%3A%2F%2Fpl-origin.ais-vidnt.com%2Fais%2Fplay%2Fanevia&tt=a33524af1d8b212d7ad71ba7d84fc3cd&chunkHttps=true&tmid=B0129&tpbk=NTlh2GKNEED9qrtX&rrt=1776261521&tmod=rfk&rsid=b54657e4-e4f0-435a-b936-eb749aec418d&tuid=09194712d8&cdn=redfox-https&tdid=8d2174919041f976a214a5ad8a720a8f&origin=anevia&tfa=f0-fc&tttl=1776347901",
      "referer": "https://49-231-34-108-rewriter.ais-vidnt.com/",
      "userAgent": "Mozilla/5.0 (Windows NT 10.0; WOW64) AppleWebKit/537.36 (KHTML, like Gecko) Chrome/69.0.3497.81 Safari/537.36 Maxthon/5.3.8.2000",
      "playInNatPlayer": "true"
    },
    {
      "name": "Parliament",
      "image": "https://ais-s.ais-vidnt.com/ais/play/origin/LIVE//channelicon/0048.png",
      "url": "https://49-231-37-229-rewriter.ais-vidnt.com/ais/play/anevia/live/eds/V0048/HLS/V0048.m3u8?playbackUrlPrefix=https%3A%2F%2Ftr.play-rbcdn.ais.co.th%3A8438%2F&originBasicUrl=http%3A%2F%2Fpl-origin.ais-vidnt.com%2Fais%2Fplay%2Fanevia&tt=a33524af1d8b212d7ad71ba7d84fc3cd&chunkHttps=true&tmid=V0048&tpbk=NTlh2GKNEED9qrtX&rrt=1776261527&tmod=rfk&rsid=d1a57d35-63d5-43ce-a86a-864fa306f8dd&tuid=09194712d8&cdn=redfox-https&tdid=8d2174919041f976a214a5ad8a720a8f&origin=anevia&tfa=f0-fc&tttl=1776347901",
      "referer": "https://49-231-34-108-rewriter.ais-vidnt.com/",
      "userAgent": "Mozilla/5.0 (Windows NT 10.0; WOW64) AppleWebKit/537.36 (KHTML, like Gecko) Chrome/69.0.3497.81 Safari/537.36 Maxthon/5.3.8.2000",
      "playInNatPlayer": "true"
    },
    {
      "name": "TNN",
      "image": "https://ais-s.ais-vidnt.com/ais/play/origin/LIVE/channelicon/R2_0053.png",
      "url": "https://49-231-37-229-rewriter.ais-vidnt.com/ais/play/anevia/live/eds/V0053/HLS/V0053.m3u8?playbackUrlPrefix=https%3A%2F%2Ftr.play-rbcdn.ais.co.th%3A8438%2F&originBasicUrl=http%3A%2F%2Fpl-origin.ais-vidnt.com%2Fais%2Fplay%2Fanevia&tt=a33524af1d8b212d7ad71ba7d84fc3cd&chunkHttps=true&tmid=V0053&tpbk=NTlh2GKNEED9qrtX&rrt=1776261533&tmod=rfk&rsid=e8a7954d-e94d-4abd-971f-6bd3ba75e0c2&tuid=09194712d8&cdn=redfox-https&tdid=8d2174919041f976a214a5ad8a720a8f&origin=anevia&tfa=f0-fc&tttl=1776347901",
      "referer": "https://49-231-34-108-rewriter.ais-vidnt.com/",
      "userAgent": "Mozilla/5.0 (Windows NT 10.0; WOW64) AppleWebKit/537.36 (KHTML, like Gecko) Chrome/69.0.3497.81 Safari/537.36 Maxthon/5.3.8.2000",
      "playInNatPlayer": "true"
    },
    {
      "name": "Nation TV",
      "image": "https://ais-s.ais-vidnt.com/ais/play/origin/LIVE/channelicon/22_Nation_2025.png",
      "url": "https://49-231-37-37-rewriter.ais-vidnt.com/ais/play/anevia/live/eds/B0021/HLS/B0021.m3u8?playbackUrlPrefix=https%3A%2F%2Ftr.play-rbcdn.ais.co.th%3A8438%2F&originBasicUrl=http%3A%2F%2Fpl-origin.ais-vidnt.com%2Fais%2Fplay%2Fanevia&tt=a33524af1d8b212d7ad71ba7d84fc3cd&chunkHttps=true&tmid=B0021&tpbk=NTlh2GKNEED9qrtX&rrt=1776261539&tmod=rfk&rsid=4850f307-0e58-4af2-8bd1-77e743d23ad7&tuid=09194712d8&cdn=redfox-https&tdid=8d2174919041f976a214a5ad8a720a8f&origin=anevia&tfa=f0-fc&tttl=1776347901",
      "referer": "https://49-231-34-108-rewriter.ais-vidnt.com/",
      "userAgent": "Mozilla/5.0 (Windows NT 10.0; WOW64) AppleWebKit/537.36 (KHTML, like Gecko) Chrome/69.0.3497.81 Safari/537.36 Maxthon/5.3.8.2000",
      "playInNatPlayer": "true"
    },
    {
      "name": "Workpoint TV",
      "image": "https://ais-s.ais-vidnt.com/ais/play/origin/LIVE/channelicon//0015_R.png",
      "url": "https://49-231-37-235-rewriter.ais-vidnt.com/ais/play/anevia/live/eds/B0015/HLS/B0015.m3u8?playbackUrlPrefix=https%3A%2F%2Ftr.play-rbcdn.ais.co.th%3A8438%2F&originBasicUrl=http%3A%2F%2Fpl-origin.ais-vidnt.com%2Fais%2Fplay%2Fanevia&tt=a33524af1d8b212d7ad71ba7d84fc3cd&chunkHttps=true&tmid=B0015&tpbk=NTlh2GKNEED9qrtX&rrt=1776261544&tmod=rfk&rsid=148f314a-440e-493c-9337-3ae01c8075cf&tuid=09194712d8&cdn=redfox-https&tdid=8d2174919041f976a214a5ad8a720a8f&origin=anevia&tfa=f0-fc&tttl=1776347901",
      "referer": "https://49-231-34-108-rewriter.ais-vidnt.com/",
      "userAgent": "Mozilla/5.0 (Windows NT 10.0; WOW64) AppleWebKit/537.36 (KHTML, like Gecko) Chrome/69.0.3497.81 Safari/537.36 Maxthon/5.3.8.2000",
      "playInNatPlayer": "true"
    },
    {
      "name": "True 4 U",
      "image": "https://ais-s.ais-vidnt.com/ais/play/origin/LIVE/channelicon/0054.png",
      "url": "https://49-231-34-108-rewriter.ais-vidnt.com/ais/play/anevia/live/eds/B0054/HLS/B0054.m3u8?playbackUrlPrefix=https%3A%2F%2Ftr.play-rbcdn.ais.co.th%3A8438%2F&originBasicUrl=http%3A%2F%2Fpl-origin.ais-vidnt.com%2Fais%2Fplay%2Fanevia&tt=a33524af1d8b212d7ad71ba7d84fc3cd&chunkHttps=true&tmid=B0054&tpbk=NTlh2GKNEED9qrtX&rrt=1776261550&tmod=rfk&rsid=41b08c6e-8d5c-416e-a729-2e7de9f231dd&tuid=09194712d8&cdn=redfox-https&tdid=8d2174919041f976a214a5ad8a720a8f&origin=anevia&tfa=f0-fc&tttl=1776347901",
      "referer": "https://49-231-34-108-rewriter.ais-vidnt.com/",
      "userAgent": "Mozilla/5.0 (Windows NT 10.0; WOW64) AppleWebKit/537.36 (KHTML, like Gecko) Chrome/69.0.3497.81 Safari/537.36 Maxthon/5.3.8.2000",
      "playInNatPlayer": "true"
    },
    {
      "name": "GMM25",
      "image": "https://ais-s.ais-vidnt.com/ais/play/origin/LIVE/channelicon/0019.png",
      "url": "https://49-231-34-107-rewriter.ais-vidnt.com/ais/play/anevia/live/eds/B0019/HLS/B0019.m3u8?playbackUrlPrefix=https%3A%2F%2Ftr.play-rbcdn.ais.co.th%3A8438%2F&originBasicUrl=http%3A%2F%2Fpl-origin.ais-vidnt.com%2Fais%2Fplay%2Fanevia&tt=a33524af1d8b212d7ad71ba7d84fc3cd&chunkHttps=true&tmid=B0019&tpbk=NTlh2GKNEED9qrtX&rrt=1776261556&tmod=rfk&rsid=1dc68196-ded8-43d3-a7cf-7f07d961cc74&tuid=09194712d8&cdn=redfox-https&tdid=8d2174919041f976a214a5ad8a720a8f&origin=anevia&tfa=f0-fc&tttl=1776347901",
      "referer": "https://49-231-34-108-rewriter.ais-vidnt.com/",
      "userAgent": "Mozilla/5.0 (Windows NT 10.0; WOW64) AppleWebKit/537.36 (KHTML, like Gecko) Chrome/69.0.3497.81 Safari/537.36 Maxthon/5.3.8.2000",
      "playInNatPlayer": "true"
    },
    {
      "name": "CH8",
      "image": "https://ais-s.ais-vidnt.com/ais/play/origin/LIVE/channelicon//CH8_2026.png",
      "url": "https://49-231-34-107-rewriter.ais-vidnt.com/ais/play/anevia/live/eds/B0006/HLS/B0006.m3u8?playbackUrlPrefix=https%3A%2F%2Ftr.play-rbcdn.ais.co.th%3A8438%2F&originBasicUrl=http%3A%2F%2Fpl-origin.ais-vidnt.com%2Fais%2Fplay%2Fanevia&tt=a33524af1d8b212d7ad71ba7d84fc3cd&chunkHttps=true&tmid=B0006&tpbk=NTlh2GKNEED9qrtX&rrt=1776261562&tmod=rfk&rsid=71292594-1bac-4546-82a1-9f483aa4ee8e&tuid=09194712d8&cdn=redfox-https&tdid=8d2174919041f976a214a5ad8a720a8f&origin=anevia&tfa=f0-fc&tttl=1776347901",
      "referer": "https://49-231-34-108-rewriter.ais-vidnt.com/",
      "userAgent": "Mozilla/5.0 (Windows NT 10.0; WOW64) AppleWebKit/537.36 (KHTML, like Gecko) Chrome/69.0.3497.81 Safari/537.36 Maxthon/5.3.8.2000",
      "playInNatPlayer": "true"
    },
    {
      "name": "MONO",
      "image": "https://ais-s.ais-vidnt.com/ais/play/origin/LIVE/channelicon/Mono_2025e.png",
      "url": "https://49-231-34-108-rewriter.ais-vidnt.com/ais/play/anevia/live/eds/W0016/HLS/W0016.m3u8?playbackUrlPrefix=https%3A%2F%2Ftr.play-rbcdn.ais.co.th%3A8438%2F&originBasicUrl=http%3A%2F%2Fpl-origin.ais-vidnt.com%2Fais%2Fplay%2Fanevia&tt=a33524af1d8b212d7ad71ba7d84fc3cd&chunkHttps=true&tmid=W0016&tpbk=NTlh2GKNEED9qrtX&rrt=1776261567&tmod=rfk&rsid=d191736f-02ca-4543-a254-3ef8686dc0d6&tuid=09194712d8&cdn=redfox-https&tdid=8d2174919041f976a214a5ad8a720a8f&origin=anevia&tfa=f0-fc&tttl=1776347901",
      "referer": "https://49-231-34-108-rewriter.ais-vidnt.com/",
      "userAgent": "Mozilla/5.0 (Windows NT 10.0; WOW64) AppleWebKit/537.36 (KHTML, like Gecko) Chrome/69.0.3497.81 Safari/537.36 Maxthon/5.3.8.2000",
      "playInNatPlayer": "true"
    },
    {
      "name": "MCOT HD",
      "image": "https://ais-s.ais-vidnt.com/ais/play/origin/LIVE/channelicon/MCOT_new.png",
      "url": "https://49-231-37-237-rewriter.ais-vidnt.com/ais/play/anevia/live/eds/B0008/HLS/B0008.m3u8?playbackUrlPrefix=https%3A%2F%2Ftr.play-rbcdn.ais.co.th%3A8438%2F&originBasicUrl=http%3A%2F%2Fpl-origin.ais-vidnt.com%2Fais%2Fplay%2Fanevia&tt=a33524af1d8b212d7ad71ba7d84fc3cd&chunkHttps=true&tmid=B0008&tpbk=NTlh2GKNEED9qrtX&rrt=1776261573&tmod=rfk&rsid=cba19e2b-d32d-49d4-802f-687f89df4683&tuid=09194712d8&cdn=redfox-https&tdid=8d2174919041f976a214a5ad8a720a8f&origin=anevia&tfa=f0-fc&tttl=1776347901",
      "referer": "https://49-231-34-108-rewriter.ais-vidnt.com/",
      "userAgent": "Mozilla/5.0 (Windows NT 10.0; WOW64) AppleWebKit/537.36 (KHTML, like Gecko) Chrome/69.0.3497.81 Safari/537.36 Maxthon/5.3.8.2000",
      "playInNatPlayer": "true"
    },
    {
      "name": "ONE 31 HD",
      "image": "https://ais-s.ais-vidnt.com/ais/play/origin/LIVE/channelicon/0012.png",
      "url": "https://49-231-37-236-rewriter.ais-vidnt.com/ais/play/anevia/live/eds/B0012/HLS/B0012.m3u8?playbackUrlPrefix=https%3A%2F%2Ftr.play-rbcdn.ais.co.th%3A8438%2F&originBasicUrl=http%3A%2F%2Fpl-origin.ais-vidnt.com%2Fais%2Fplay%2Fanevia&tt=a33524af1d8b212d7ad71ba7d84fc3cd&chunkHttps=true&tmid=B0012&tpbk=NTlh2GKNEED9qrtX&rrt=1776261579&tmod=rfk&rsid=f1223e84-586d-4528-be71-3192a155ba4c&tuid=09194712d8&cdn=redfox-https&tdid=8d2174919041f976a214a5ad8a720a8f&origin=anevia&tfa=f0-fc&tttl=1776347901",
      "referer": "https://49-231-34-108-rewriter.ais-vidnt.com/",
      "userAgent": "Mozilla/5.0 (Windows NT 10.0; WOW64) AppleWebKit/537.36 (KHTML, like Gecko) Chrome/69.0.3497.81 Safari/537.36 Maxthon/5.3.8.2000",
      "playInNatPlayer": "true"
    },
    {
      "name": "Thairath TV HD",
      "image": "https://ais-s.ais-vidnt.com/ais/play/origin/LIVE/channelicon/0013_R.png",
      "url": "https://49-231-34-109-rewriter.ais-vidnt.com/ais/play/anevia/live/eds/B0013/HLS/B0013.m3u8?playbackUrlPrefix=https%3A%2F%2Ftr.play-rbcdn.ais.co.th%3A8438%2F&originBasicUrl=http%3A%2F%2Fpl-origin.ais-vidnt.com%2Fais%2Fplay%2Fanevia&tt=a33524af1d8b212d7ad71ba7d84fc3cd&chunkHttps=true&tmid=B0013&tpbk=NTlh2GKNEED9qrtX&rrt=1776261585&tmod=rfk&rsid=3b97dd14-4b4e-4091-9fdf-50aa97d23768&tuid=09194712d8&cdn=redfox-https&tdid=8d2174919041f976a214a5ad8a720a8f&origin=anevia&tfa=f0-fc&tttl=1776347901",
      "referer": "https://49-231-34-108-rewriter.ais-vidnt.com/",
      "userAgent": "Mozilla/5.0 (Windows NT 10.0; WOW64) AppleWebKit/537.36 (KHTML, like Gecko) Chrome/69.0.3497.81 Safari/537.36 Maxthon/5.3.8.2000",
      "playInNatPlayer": "true"
    },
    {
      "name": "3 HD",
      "image": "https://ais-s.ais-vidnt.com/ais/play/origin/LIVE//channelicon/LOGO3HD.PNG",
      "url": "https://49-231-37-235-rewriter.ais-vidnt.com/ais/play/anevia/live/eds/B0003/HLS/B0003.m3u8?playbackUrlPrefix=https%3A%2F%2Ftr.play-rbcdn.ais.co.th%3A8438%2F&originBasicUrl=http%3A%2F%2Fpl-origin.ais-vidnt.com%2Fais%2Fplay%2Fanevia&tt=a33524af1d8b212d7ad71ba7d84fc3cd&chunkHttps=true&tmid=B0003&tpbk=NTlh2GKNEED9qrtX&rrt=1776261590&tmod=rfk&rsid=18b8569f-10a0-47f6-8fd3-34e3236b5f91&tuid=09194712d8&cdn=redfox-https&tdid=8d2174919041f976a214a5ad8a720a8f&origin=anevia&tfa=f0-fc&tttl=1776347901",
      "referer": "https://49-231-34-108-rewriter.ais-vidnt.com/",
      "userAgent": "Mozilla/5.0 (Windows NT 10.0; WOW64) AppleWebKit/537.36 (KHTML, like Gecko) Chrome/69.0.3497.81 Safari/537.36 Maxthon/5.3.8.2000",
      "playInNatPlayer": "true"
    },
    {
      "name": "AmarinTV HD",
      "image": "https://ais-s.ais-vidnt.com/ais/play/origin/LIVE//channelicon/AmarinTV_NEW512.png",
      "url": "https://49-231-37-229-rewriter.ais-vidnt.com/ais/play/anevia/live/eds/B0017/HLS/B0017.m3u8?playbackUrlPrefix=https%3A%2F%2Ftr.play-rbcdn.ais.co.th%3A8438%2F&originBasicUrl=http%3A%2F%2Fpl-origin.ais-vidnt.com%2Fais%2Fplay%2Fanevia&tt=a33524af1d8b212d7ad71ba7d84fc3cd&chunkHttps=true&tmid=B0017&tpbk=NTlh2GKNEED9qrtX&rrt=1776261596&tmod=rfk&rsid=d5fdd94c-4a95-4966-8e41-589a991e839d&tuid=09194712d8&cdn=redfox-https&tdid=8d2174919041f976a214a5ad8a720a8f&origin=anevia&tfa=f0-fc&tttl=1776347901",
      "referer": "https://49-231-34-108-rewriter.ais-vidnt.com/",
      "userAgent": "Mozilla/5.0 (Windows NT 10.0; WOW64) AppleWebKit/537.36 (KHTML, like Gecko) Chrome/69.0.3497.81 Safari/537.36 Maxthon/5.3.8.2000",
      "playInNatPlayer": "true"
    },
    {
      "name": "CH7 HD",
      "image": "https://ais-s.ais-vidnt.com/ais/play/origin/LIVE//channelicon/0018.png",
      "url": "https://49-231-34-108-rewriter.ais-vidnt.com/ais/play/anevia/live/eds/B0018/HLS/B0018.m3u8?playbackUrlPrefix=https%3A%2F%2Ftr.play-rbcdn.ais.co.th%3A8438%2F&originBasicUrl=http%3A%2F%2Fpl-origin.ais-vidnt.com%2Fais%2Fplay%2Fanevia&tt=a33524af1d8b212d7ad71ba7d84fc3cd&chunkHttps=true&tmid=B0018&tpbk=NTlh2GKNEED9qrtX&rrt=1776261602&tmod=rfk&rsid=9dc67321-0ab9-46f7-b267-29ecba14ea5f&tuid=09194712d8&cdn=redfox-https&tdid=8d2174919041f976a214a5ad8a720a8f&origin=anevia&tfa=f0-fc&tttl=1776347901",
      "referer": "https://49-231-34-108-rewriter.ais-vidnt.com/",
      "userAgent": "Mozilla/5.0 (Windows NT 10.0; WOW64) AppleWebKit/537.36 (KHTML, like Gecko) Chrome/69.0.3497.81 Safari/537.36 Maxthon/5.3.8.2000",
      "playInNatPlayer": "true"
    },
    {
      "name": "PPTV HD",
      "image": "https://ais-s.ais-vidnt.com/ais/play/origin/LIVE/channelicon/PPTV_2024e.jpg",
      "url": "https://49-231-37-229-rewriter.ais-vidnt.com/ais/play/anevia/live/eds/B0022/HLS/B0022.m3u8?playbackUrlPrefix=https%3A%2F%2Ftr.play-rbcdn.ais.co.th%3A8438%2F&originBasicUrl=http%3A%2F%2Fpl-origin.ais-vidnt.com%2Fais%2Fplay%2Fanevia&tt=a33524af1d8b212d7ad71ba7d84fc3cd&chunkHttps=true&tmid=B0022&tpbk=NTlh2GKNEED9qrtX&rrt=1776261607&tmod=rfk&rsid=839a38a7-ab13-4e42-9088-32b0e0d1614c&tuid=09194712d8&cdn=redfox-https&tdid=8d2174919041f976a214a5ad8a720a8f&origin=anevia&tfa=f0-fc&tttl=1776347901",
      "referer": "https://49-231-34-108-rewriter.ais-vidnt.com/",
      "userAgent": "Mozilla/5.0 (Windows NT 10.0; WOW64) AppleWebKit/537.36 (KHTML, like Gecko) Chrome/69.0.3497.81 Safari/537.36 Maxthon/5.3.8.2000",
      "playInNatPlayer": "true"
    },
    {
      "name": "Boomerang",
      "image": "https://ais-s.ais-vidnt.com/ais/play/origin/LIVE/channelicon/Boomerang_2025.png",
      "url": "https://49-231-37-37-rewriter.ais-vidnt.com/ais/play/anevia/live/eds/V0104/HLS/V0104.m3u8?playbackUrlPrefix=https%3A%2F%2Ftr.play-rbcdn.ais.co.th%3A8438%2F&originBasicUrl=http%3A%2F%2Fpl-origin.ais-vidnt.com%2Fais%2Fplay%2Fanevia&tt=a33524af1d8b212d7ad71ba7d84fc3cd&chunkHttps=true&tmid=V0104&tpbk=NTlh2GKNEED9qrtX&rrt=1776261613&tmod=rfk&rsid=17b68377-c72e-43c2-b0e9-a1d6e5ff193e&tuid=09194712d8&cdn=redfox-https&tdid=8d2174919041f976a214a5ad8a720a8f&origin=anevia&tfa=f0-fc&tttl=1776347901",
      "referer": "https://49-231-34-108-rewriter.ais-vidnt.com/",
      "userAgent": "Mozilla/5.0 (Windows NT 10.0; WOW64) AppleWebKit/537.36 (KHTML, like Gecko) Chrome/69.0.3497.81 Safari/537.36 Maxthon/5.3.8.2000",
      "playInNatPlayer": "true"
    },
    {
      "name": "TOP News",
      "image": "https://ais-s.ais-vidnt.com/ais/play/origin/LIVE//channelicon/TOPNEWS.PNG",
      "url": "https://49-231-37-236-rewriter.ais-vidnt.com/ais/play/anevia/live/eds/V0033/HLS/V0033.m3u8?playbackUrlPrefix=https%3A%2F%2Ftr.play-rbcdn.ais.co.th%3A8438%2F&originBasicUrl=http%3A%2F%2Fpl-origin.ais-vidnt.com%2Fais%2Fplay%2Fanevia&tt=a33524af1d8b212d7ad71ba7d84fc3cd&chunkHttps=true&tmid=V0033&tpbk=NTlh2GKNEED9qrtX&rrt=1776261619&tmod=rfk&rsid=76539fbc-788e-44c8-8596-af726c16a31c&tuid=09194712d8&cdn=redfox-https&tdid=8d2174919041f976a214a5ad8a720a8f&origin=anevia&tfa=f0-fc&tttl=1776347901",
      "referer": "https://49-231-34-108-rewriter.ais-vidnt.com/",
      "userAgent": "Mozilla/5.0 (Windows NT 10.0; WOW64) AppleWebKit/537.36 (KHTML, like Gecko) Chrome/69.0.3497.81 Safari/537.36 Maxthon/5.3.8.2000",
      "playInNatPlayer": "true"
    },
    {
      "name": "News 1",
      "image": "https://ais-s.ais-vidnt.com/ais/play/origin/LIVE/channelicon/0036.png",
      "url": "https://49-231-37-236-rewriter.ais-vidnt.com/ais/play/anevia/live/eds/V0036/HLS/V0036.m3u8?playbackUrlPrefix=https%3A%2F%2Ftr.play-rbcdn.ais.co.th%3A8438%2F&originBasicUrl=http%3A%2F%2Fpl-origin.ais-vidnt.com%2Fais%2Fplay%2Fanevia&tt=a33524af1d8b212d7ad71ba7d84fc3cd&chunkHttps=true&tmid=V0036&tpbk=NTlh2GKNEED9qrtX&rrt=1776261625&tmod=rfk&rsid=efb6279a-6fcb-444d-a431-949427201d2d&tuid=09194712d8&cdn=redfox-https&tdid=8d2174919041f976a214a5ad8a720a8f&origin=anevia&tfa=f0-fc&tttl=1776347901",
      "referer": "https://49-231-34-108-rewriter.ais-vidnt.com/",
      "userAgent": "Mozilla/5.0 (Windows NT 10.0; WOW64) AppleWebKit/537.36 (KHTML, like Gecko) Chrome/69.0.3497.81 Safari/537.36 Maxthon/5.3.8.2000",
      "playInNatPlayer": "true"
    },
    {
      "name": "LunthungTV",
      "image": "https://ais-s.ais-vidnt.com/ais/play/origin/LIVE//channelicon/LunthungTV.PNG",
      "url": "https://49-231-37-229-rewriter.ais-vidnt.com/ais/play/anevia/live/eds/V0092/HLS/V0092.m3u8?playbackUrlPrefix=https%3A%2F%2Ftr.play-rbcdn.ais.co.th%3A8438%2F&originBasicUrl=http%3A%2F%2Fpl-origin.ais-vidnt.com%2Fais%2Fplay%2Fanevia&tt=a33524af1d8b212d7ad71ba7d84fc3cd&chunkHttps=true&tmid=V0092&tpbk=NTlh2GKNEED9qrtX&rrt=1776261630&tmod=rfk&rsid=ac048db3-8a3a-4068-86da-e7e14f4a875c&tuid=09194712d8&cdn=redfox-https&tdid=8d2174919041f976a214a5ad8a720a8f&origin=anevia&tfa=f0-fc&tttl=1776347901",
      "referer": "https://49-231-34-108-rewriter.ais-vidnt.com/",
      "userAgent": "Mozilla/5.0 (Windows NT 10.0; WOW64) AppleWebKit/537.36 (KHTML, like Gecko) Chrome/69.0.3497.81 Safari/537.36 Maxthon/5.3.8.2000",
      "playInNatPlayer": "true"
    },
    {
      "name": "MVTV",
      "image": "https://ais-s.ais-vidnt.com/ais/play/origin/LIVE//channelicon/MVTV.png",
      "url": "https://49-231-34-107-rewriter.ais-vidnt.com/ais/play/anevia/live/eds/V0090/HLS/V0090.m3u8?playbackUrlPrefix=https%3A%2F%2Ftr.play-rbcdn.ais.co.th%3A8438%2F&originBasicUrl=http%3A%2F%2Fpl-origin.ais-vidnt.com%2Fais%2Fplay%2Fanevia&tt=a33524af1d8b212d7ad71ba7d84fc3cd&chunkHttps=true&tmid=V0090&tpbk=NTlh2GKNEED9qrtX&rrt=1776261636&tmod=rfk&rsid=68040ea4-4ecf-4acd-aa08-67a9fc34bfb9&tuid=09194712d8&cdn=redfox-https&tdid=8d2174919041f976a214a5ad8a720a8f&origin=anevia&tfa=f0-fc&tttl=1776347901",
      "referer": "https://49-231-34-108-rewriter.ais-vidnt.com/",
      "userAgent": "Mozilla/5.0 (Windows NT 10.0; WOW64) AppleWebKit/537.36 (KHTML, like Gecko) Chrome/69.0.3497.81 Safari/537.36 Maxthon/5.3.8.2000",
      "playInNatPlayer": "true"
    }
  ]
}